ADQL/adql.py
ADQL/jcg.py
ADQL/test.py
ADQL-1.0.6.dist-info/METADATA
ADQL-1.0.6.dist-info/RECORD
ADQL-1.0.6.dist-info/WHEEL
ADQL-1.0.6.dist-info/top_level.txt
