Metadata-Version: 2.1
Name: ADQL
Version: 1.0.6
Summary: Utility for converting ADQL to local SQL syntax.
Home-page: https://github.com/Caltech-IPAC/ADQL
Author: John Good
Author-email: jcg@ipac.caltech.edu
License: LICENSE
Keywords: astronomy database ADQL SQL
Platform: UNKNOWN
Requires-Dist: spatial-index
